blessings/__init__.py
blessings/tests.py
blessings-1.6.1.dist-info/DESCRIPTION.rst
blessings-1.6.1.dist-info/METADATA
blessings-1.6.1.dist-info/RECORD
blessings-1.6.1.dist-info/WHEEL
blessings-1.6.1.dist-info/metadata.json
blessings-1.6.1.dist-info/top_level.txt
