Metadata-Version: 1.1
Name: blessings
Version: 1.6.1
Summary: A thin, practical wrapper around terminal coloring, styling, and positioning
Home-page: https://github.com/erikrose/blessings
Author: Erik Rose
Author-email: erikrose@grinchcentral.com
License: MIT
Keywords: terminal,tty,curses,ncurses,formatting,style,color,console
Platform: UNKNOWN
Classifier: Intended Audience :: Developers
Classifier: Natural Language :: English
Classifier: Development Status :: 5 - Production/Stable
Classifier: Environment :: Console
Classifier: Environment :: Console :: Curses
Classifier: License :: OSI Approved :: MIT License
Classifier: Operating System :: POSIX
Classifier: Programming Language :: Python :: 2
Classifier: Programming Language :: Python :: 2.5
Classifier: Programming Language :: Python :: 2.6
Classifier: Programming Language :: Python :: 2.7
Classifier: Programming Language :: Python :: 3
Classifier: Programming Language :: Python :: 3.2
Classifier: Topic :: Software Development :: Libraries
Classifier: Topic :: Software Development :: User Interfaces
Classifier: Topic :: Terminals
